randomwalk/__init__.py
randomwalk/resume.py
randomwalk-0.1.1.dist-info/licenses/LICENSE
randomwalk-0.1.1.dist-info/METADATA
randomwalk-0.1.1.dist-info/WHEEL
randomwalk-0.1.1.dist-info/entry_points.txt
randomwalk-0.1.1.dist-info/top_level.txt
randomwalk-0.1.1.dist-info/RECORD
