Metadata-Version: 2.4
Name: randomwalk
Version: 0.1.1
Summary: A command line tool to display a resume with colorful typewriter effect.
Home-page: https://github.com/rahulrajpl/randomwalk
Author: Rahul Raj
Author-email: rahulrajpl@gmail.com
Classifier: Programming Language :: Python :: 3
Classifier: License :: OSI Approved :: MIT License
Classifier: Operating System :: OS Independent
Requires-Python: >=3.6
License-File: LICENSE
Requires-Dist: rich
Dynamic: author
Dynamic: author-email
Dynamic: classifier
Dynamic: description
Dynamic: description-content-type
Dynamic: home-page
Dynamic: license-file
Dynamic: requires-dist
Dynamic: requires-python
Dynamic: summary
